anybt.py
anybt-1.1.0.dist-info/LICENSE
anybt-1.1.0.dist-info/METADATA
anybt-1.1.0.dist-info/WHEEL
anybt-1.1.0.dist-info/entry_points.txt
anybt-1.1.0.dist-info/RECORD
