Metadata-Version: 2.1
Name: anybt
Version: 1.1.0
Summary: An Open Sourced Decentralized BitTorrent Search Engine
Author: j2qk3b
Requires-Python: >=3.7,<4.0
Classifier: Programming Language :: Python :: 3
Classifier: Programming Language :: Python :: 3.7
Classifier: Programming Language :: Python :: 3.8
Classifier: Programming Language :: Python :: 3.9
Classifier: Programming Language :: Python :: 3.10
Classifier: Programming Language :: Python :: 3.11
Requires-Dist: requests (==2.29.0)
Requires-Dist: rich (>=13.7.1,<14.0.0)
